README.md
setup.py
apfake/__init__.py
apfake/utils.py
apfake.egg-info/PKG-INFO
apfake.egg-info/SOURCES.txt
apfake.egg-info/dependency_links.txt
apfake.egg-info/entry_points.txt
apfake.egg-info/requires.txt
apfake.egg-info/top_level.txt