Metadata-Version: 2.1
Name: apfake
Version: 0.0.2
Summary: Command-line interface for extrapolating test data from a single AP API JSON file.
Home-page: https://github.com/newsdev/apfake
Author: Jeremy Bowers
Author-email: jeremy.bowers@nytimes.com
License: Apache License 2.0
Keywords: election race candidate democracy news associated press
Platform: UNKNOWN
Classifier: Development Status :: 5 - Production/Stable
Classifier: Intended Audience :: Developers
Classifier: Topic :: Software Development :: Libraries :: Python Modules
Classifier: Programming Language :: Python
Classifier: Programming Language :: Python :: 3
Classifier: Programming Language :: Python :: 3.6
